<?xml version="1.0" encoding="utf-8" ?><dwsync><file name="2016IKNS1.jpg" server="rfa001.worldsecuresystems.com" local="3575478701" remote="3575478701" Dst="-1" /><file name="2016IKNS10.jpg" server="rfa001.worldsecuresystems.com" local="3575478701" remote="3575478701" Dst="-1" /><file name="2016IKNS2.jpg" server="rfa001.worldsecuresystems.com" local="3575478702" remote="3575478702" Dst="-1" /><file name="2016IKNS3.jpg" server="rfa001.worldsecuresystems.com" local="3575478704" remote="3575478704" Dst="-1" /><file name="2016IKNS4.jpg" server="rfa001.worldsecuresystems.com" local="3575478704" remote="3575478704" Dst="-1" /><file name="2016IKNS5.jpg" server="rfa001.worldsecuresystems.com" local="3575478705" remote="3575478705" Dst="-1" /><file name="2016IKNS6.jpg" server="rfa001.worldsecuresystems.com" local="3575478706" remote="3575478706" Dst="-1" /><file name="2016IKNS7.jpg" server="rfa001.worldsecuresystems.com" local="3575478706" remote="3575478706" Dst="-1" /><file name="2016IKNS8.jpg" server="rfa001.worldsecuresystems.com" local="3575478707" remote="3575478707" Dst="-1" /></dwsync>